Metadata-Version: 1.1
Name: pymongoback
Version: 1.0.0
Summary: PyMongo Back is a simple Python library designed to help you create MongoDB Backups from both local and remote servers.
Home-page: https://github.com/RafaMunoz/PyMongoBack
Author: Rafa Munoz
Author-email: rafa93m@gmail.com
License: MIT
Keywords: tools sysadmin backup mongodb mongodump
Platform: UNKNOWN
Classifier: Programming Language :: Python
Classifier: License :: OSI Approved :: MIT License
Classifier: Environment :: Console
Classifier: Topic :: Database
Classifier: Topic :: Software Development :: Build Tools
Classifier: Topic :: System :: Archiving :: Backup
Classifier: Intended Audience :: System Administrators
